coreason_simulacrum/__init__.py
coreason_simulacrum/chaos.py
coreason_simulacrum/interfaces.py
coreason_simulacrum/main.py
coreason_simulacrum/prompts.py
coreason_simulacrum/schemas.py
coreason_simulacrum/server.py
coreason_simulacrum/state.py
coreason_simulacrum/testing/mocks.py
coreason_simulacrum/utils/__init__.py
coreason_simulacrum/utils/logger.py
coreason_simulacrum/utils/model_utils.py
coreason_simulacrum/workflow.py
coreason_simulacrum-0.3.0.dist-info/METADATA
coreason_simulacrum-0.3.0.dist-info/WHEEL
coreason_simulacrum-0.3.0.dist-info/entry_points.txt
coreason_simulacrum-0.3.0.dist-info/licenses/LICENSE
coreason_simulacrum-0.3.0.dist-info/licenses/NOTICE
coreason_simulacrum-0.3.0.dist-info/RECORD
