Metadata-Version: 2.4
Name: coreason_simulacrum
Version: 0.3.0
Summary: coreason-simulacrum
License: # The Prosperity Public License 3.0.0
License-File: LICENSE
License-File: NOTICE
Author: Gowtham A Rao
Author-email: gowtham.rao@coreason.ai
Requires-Python: >=3.11
Classifier: License :: Other/Proprietary License
Classifier: Programming Language :: Python :: 3.12
Classifier: Operating System :: OS Independent
Requires-Dist: aiofiles (>=25.1.0,<26.0.0)
Requires-Dist: anyio (>=4.12.1,<5.0.0)
Requires-Dist: coreason-identity (>=0.4.2,<0.5.0)
Requires-Dist: fastapi (>=0.128.0,<0.129.0)
Requires-Dist: httpx (>=0.28.1,<0.29.0)
Requires-Dist: langgraph (>=1.0.7,<2.0.0)
Requires-Dist: loguru (>=0.7.2,<0.8.0)
Requires-Dist: pydantic (>=2.12.5,<3.0.0)
Requires-Dist: uvicorn (>=0.40.0,<0.41.0)
Project-URL: Documentation, https://github.com/CoReason-AI/coreason_simulacrum
Project-URL: Homepage, https://github.com/CoReason-AI/coreason_simulacrum
Project-URL: Repository, https://github.com/CoReason-AI/coreason_simulacrum
